__init__.py
__main__.py
api.py
cli.py
config.py
gitcode_hub.py
utils.py
gitcode/__init__.py
gitcode/__main__.py
gitcode/api.py
gitcode/cli.py
gitcode/config.py
gitcode/gitcode_hub.py
gitcode/utils.py
gitcode-1.2.0.dist-info/METADATA
gitcode-1.2.0.dist-info/WHEEL
gitcode-1.2.0.dist-info/entry_points.txt
gitcode-1.2.0.dist-info/top_level.txt
gitcode-1.2.0.dist-info/RECORD
