Metadata-Version: 2.4
Name: gitcode
Version: 1.2.0
Summary: GitCode模型文件上传下载CLI工具
Home-page: https://gitcode.com/gitcode-ai/gitcode_cli
Author: GitCode CLI Team
Author-email: sa@gitcode.com
Project-URL: Bug Reports, https://gitcode.com/gitcode-ai/gitcode_cli/issues
Project-URL: Source, https://gitcode.com/gitcode-ai/gitcode_cli
Keywords: openmind model dataset upload download cli
Classifier: Development Status :: 4 - Beta
Classifier: Intended Audience :: Developers
Classifier: License :: OSI Approved :: MIT License
Classifier: Operating System :: OS Independent
Classifier: Programming Language :: Python :: 3
Classifier: Programming Language :: Python :: 3.8
Classifier: Programming Language :: Python :: 3.9
Classifier: Programming Language :: Python :: 3.10
Classifier: Programming Language :: Python :: 3.11
Classifier: Programming Language :: Python :: 3.12
Classifier: Programming Language :: Python :: 3.13
Classifier: Topic :: Software Development :: Libraries :: Python Modules
Classifier: Topic :: System :: Archiving
Classifier: Topic :: Utilities
Requires-Python: >=3.8
Requires-Dist: click>=8.1.7
Requires-Dist: requests>=2.31.0
Requires-Dist: tqdm>=4.66.1
Requires-Dist: colorama>=0.4.6
Requires-Dist: tabulate>=0.9.0
Requires-Dist: openmind-hub>=1.0.0
Dynamic: author
Dynamic: author-email
Dynamic: classifier
Dynamic: description
Dynamic: description-content-type
Dynamic: home-page
Dynamic: keywords
Dynamic: project-url
Dynamic: requires-dist
Dynamic: requires-python
Dynamic: summary
